revelio/Path.py
revelio/__init__.py
revelio/dir.py
revelio/get_basename.py
revelio-0.1.1.dist-info/LICENSE
revelio-0.1.1.dist-info/METADATA
revelio-0.1.1.dist-info/WHEEL
revelio-0.1.1.dist-info/top_level.txt
revelio-0.1.1.dist-info/RECORD
