Metadata-Version: 2.1
Name: revelio
Version: 0.1.1
Summary: Python library for interacting with the file system
Home-page: https://github.com/idin/revelio
Author: Idin K
Author-email: py@idin.ca
License: MIT
Platform: UNKNOWN
Requires-Python: ~=3.6
